{
  "products": [
    {
      "id": 1,
      "model": "Carnival",
      "year": "2022",
      "power": "249",
      "kuzov": "Кроссвэн",
      "transmission": "АКПП",
      "engine": "Бензин",
      "color": "Красный",
      "price": 4934900,
      "image": "https://cdn.kia.ru/resize/1295x632/master-data/albums/carnival/C7R/1.png"
    },

    {
      "id": 2,
      "model": "Ceed",
      "year": "2022",
      "power": "128",
      "kuzov": "Хэтчбек",
      "transmission": "АКПП",
      "engine": "Бензин",
      "color": "Черный",
      "price": 2614900,
      "image": "https://cdn.kia.ru/resize/1295x632/master-data/albums/ceed_new/premium/H8G/1.png"
    },
    {
      "id": 3,
      "model": "Ceed SW",
      "year": "2022",
      "power": "128",
      "kuzov": "Универсал",
      "transmission": "АКПП",
      "engine": "Бензин",
      "color": "Черный",
      "price": 3194900,
      "image": "https://cdn.kia.ru/resize/1295x632/master-data/albums/ceed_sw_new/premium/1K/1.png"
    },
    {
      "id": 4,
      "model": "Cerato",
      "year": "2022",
      "power": "128",
      "kuzov": "Седан",
      "transmission": "МКПП",
      "engine": "Бензин",
      "color": "Серый",
      "price": 2970000,
      "image": "https://cdn.kia.ru/resize/1295x632/master-data/albums/ceed_sw_new/premium/1K/1.png"
    },
    {
      "id": 5,
      "model": "K5",
      "year": "2022",
      "power": "150",
      "kuzov": "Седан",
      "transmission": "АКПП",
      "engine": "Бензин",
      "color": "Белый",
      "price": 2734900,
      "image": "https://cdn.kia.ru/resize/1295x632/master-data/albums/k5/classic/UD/1.png"
    },
    {
      "id": 6,
      "model": "K9",
      "year": "2022",
      "power": "249",
      "kuzov": "Седан",
      "transmission": "АКПП",
      "engine": "Бензин",
      "color": "Черный",
      "price": 7374900,
      "image": "https://cdn.kia.ru/resize/1295x632/master-data/albums/k9/premium/ABP/1.png"
    },
    {
      "id": 7,
      "model": "Rio X",
      "year": "2022",
      "power": "123",
      "kuzov": "Хэтчбек",
      "transmission": "АКПП",
      "engine": "Бензин",
      "color": "Коричневый",
      "price": 2545900,
      "image": "https://cdn.kia.ru/resize/1295x632/master-data/albums/rio-x/S5P/1.png"
    },
    {
      "id": 8,
      "model": "Seltos",
      "year": "2022",
      "power": "149",
      "kuzov": "Кроссовер",
      "transmission": "Вариатор",
      "engine": "Бензин",
      "color": "Синий",
      "price": 2799900,
      "image": "https://cdn.kia.ru/resize/1295x632/master-data/albums/seltos/prestige/B3A/1.png"
    },
    {
      "id": 9,
      "model": "Sorento",
      "year": "2022",
      "power": "179",
      "kuzov": "Кроссовер",
      "transmission": "АКПП",
      "engine": "Бензин",
      "color": "Серебристый",
      "price": 4344900,
      "image": "https://cdn.kia.ru/resize/1295x632/master-data/albums/3da79ef4-21f8-4f46-a216-c7e3429dc2cc.png"
    },
    {
      "id": 10,
      "model": "Soul",
      "year": "2022",
      "power": "123",
      "kuzov": "Кроссовер",
      "transmission": "АКПП",
      "engine": "Бензин",
      "color": "Синий",
      "price": 2204900,
      "image": "https://cdn.kia.ru/resize/1295x632/master-data/albums/soul/B4U/1.png"
    },
    {
      "id": 11,
      "model": "Sportage",
      "year": "2022",
      "power": "190",
      "kuzov": "Кроссовер",
      "transmission": "АКПП",
      "engine": "Бензин",
      "color": "Черный",
      "price": 4823200,
      "image": "https://cdn.kia.ru/resize/1295x632/master-data/albums/sportage_new/prestige/FSB/1.png"
    },
    {
      "id": 12,
      "model": "Stinger",
      "year": "2022",
      "power": "247",
      "kuzov": "Седан",
      "transmission": "АКПП",
      "engine": "Бензин",
      "color": "Синий",
      "price": 5374900,
      "image": "https://cdn.kia.ru/resize/1295x632/master-data/albums/stinger_new/D9B/1.png"
    }
  ]
}